Metadata-Version: 2.1
Name: qt5-t5darkstyle
Version: 1.1
Summary: Dark Stylesheet for QT5
Home-page: https://gitlab.com/t-5/qt5_t5darkstyle
Author: Jürgen Herrmann
Author-email: t-5@t-5.eu
License: bsd-3-clause
Platform: UNKNOWN
Requires-Python: >=3
